Workbook
Name aporte: Simulador!$D$17
Name Aporte_mensal: Simulador!$C$18
Name Rendimento: Simulador!$D$12
Name rendimento_carteira: Simulador!#REF!
Name Taxa: Simulador!$C$19
Name Tempo: Simulador!$C$22

Sheet Simulador
B10: Rendimento Carteira
B11: Salário | D11: 4200
B12: Rendimento Carteira | D12: 0.01
B13: Sugestão de Investimento (30%) | D13: =D11*30% -> 1260
B15: TABELA DE RENDIMENTOS
A17: 2 | B17: APORTE INICIAL | C17: 2000
A18: 5 | B18: APORTE MENSAL | C18: =D13 -> 1260
A19: 10 | B19: TAXA DE RENDIMENTO | C19: 0.01079
A20: 20 | B20: DIVIDENDOS MENSAIS | C20: =C21*Taxa -> 3307.5462
A21: 30 | B21: VALOR DA COTA | C21: =FV(C19,C22*12,C18*-1) -> 306538.11
B22: TEMPO | C22: 10
B24: Crescimento Patrimonial | D24: Dividendo
B25: 2 anos | C25: =FV($C$19,A17*12,$C$18*-1) -> 34306.81 | D25: =C25*Taxa -> 370.17048
B26: 5 anos | C26: =FV($C$19,A$18*12,C18*-1) -> 105558.91 | D26: =C26*Taxa -> 1138.9807
B27: 10 anos | C27: =FV(C19,A19*12,C18*-1) -> 306538.11 | D27: =C27*Taxa -> 3307.5462
B28: 20 anos | C28: =FV(C19,A20*12,C18*-1) -> 1417750 | D28: =C28*Taxa -> 15297.522
B29: 30 anos | C29: =FV(C19,A21*12,C18*-1) -> 5445933.8 | D29: =C29*Taxa -> 58761.625
B31: PERFIL | C31: Moderado
B32: VALOR A SER INVESTIDO POR MÊS | C32: =Aporte_mensal -> 1260
B34: TIPO DE FII | C34: Percentual Sugerido | D34: Valores
B35: PAPEL | C35: =VLOOKUP($C$31&"-"&B35,Investidor!A2:D20,4,FALSE) -> 0.32 | D35: =C35*$C$32 -> 403.2
B36: TIJOLO | C36: =VLOOKUP($C$31&"-"&B36,Investidor!A3:D21,4,FALSE) -> 0.35 | D36: =C36*$C$32 -> 441
B37: HÍBRIDOS | C37: =VLOOKUP($C$31&"-"&B37,Investidor!A4:D22,4,FALSE) -> 0.08 | D37: =C37*$C$32 -> 100.8
B38: FOFs | C38: =VLOOKUP($C$31&"-"&B38,Investidor!A5:D23,4,FALSE) -> 0.05 | D38: =C38*$C$32 -> 63
B39: DESENVOLVIMENTO | C39: =VLOOKUP($C$31&"-"&B39,Investidor!A6:D24,4,FALSE) -> 0.1 | D39: =C39*$C$32 -> 126
B40: HOTELARIAS | C40: =VLOOKUP($C$31&"-"&B40,Investidor!A7:D25,4,FALSE) -> 0.1 | D40: =C40*$C$32 -> 126
D41: =SUM(D35:D40) -> 1260

Sheet Investidor
A2: CHAVE | B2: PERFIL | C2: TIPO DE FII | D2: %
A3: =B3&"-"&C3 -> Conservador-PAPEL | B3: Conservador | C3: PAPEL | D3: 0.3 | G3: =VLOOKUP(F3,A2:D20,4,FALSE) -> #N/A | H3: %
A4: =B4&"-"&C4 -> Conservador-TIJOLO | B4: Conservador | C4: TIJOLO | D4: 0.5
A5: =B5&"-"&C5 -> Conservador-HÍBRIDOS | B5: Conservador | C5: HÍBRIDOS | D5: 0.1
A6: =B6&"-"&C6 -> Conservador-FOFs | B6: Conservador | C6: FOFs | D6: 0.1
A7: =B7&"-"&C7 -> Conservador-DESENVOLVIMENTO | B7: Conservador | C7: DESENVOLVIMENTO | D7: 0
A8: =B8&"-"&C8 -> Conservador-HOTELARIAS | B8: Conservador | C8: HOTELARIAS | D8: 0
A9: =B9&"-"&C9 -> Moderado-PAPEL | B9: Moderado | C9: PAPEL | D9: 0.32
A10: =B10&"-"&C10 -> Moderado-TIJOLO | B10: Moderado | C10: TIJOLO | D10: 0.35
A11: =B11&"-"&C11 -> Moderado-HÍBRIDOS | B11: Moderado | C11: HÍBRIDOS | D11: 0.08
A12: =B12&"-"&C12 -> Moderado-FOFs | B12: Moderado | C12: FOFs | D12: 0.05
A13: =B13&"-"&C13 -> Moderado-DESENVOLVIMENTO | B13: Moderado | C13: DESENVOLVIMENTO | D13: 0.1
A14: =B14&"-"&C14 -> Moderado-HOTELARIAS | B14: Moderado | C14: HOTELARIAS | D14: 0.1
A15: =B15&"-"&C15 -> Agressivo-PAPEL | B15: Agressivo | C15: PAPEL | D15: 0.5
... A20: =B20&"-"&C20 -> Agressivo-HOTELARIAS | B20: Agressivo | C20: HOTELARIAS | D20: 0.1

Sheet Dados 
A2: Simulador de Investimento em Fundos Imobiliários (FIIs)
A4: Este projeto foi desenvolvido como parte de um desafio da Dio.
A5: Com o objetivo de criar uma ferramenta prática que auxilie um investidor a simular seu plano de investimento e patrimônio.
A6: A planilha permite:
A8: 1. | B8: Simular o Patrimônio - Projeção de valor futuro através da Formuça (VF)
A9: 2. | B9: Calcular o lucro real - diferenciar entre capital investido e os juros acumulados ]
A10: 3. | B10: Análise a longo prazo - utilizando tabela comparativa de rendimentos (períodos anuais)
A13: Como utilizá-la
A15: 1. | B15: Insira o valor inicial (investimento)
A16: 2. | B16: Definir o aporte (quanto poupar por mês)
A17: 3. | B17: Informar a taxa de rendimentos (mensal)
A19: Desenvolvido por: | C19: Simone Daloz
A20: linkedin/simonedaloz
